framewatchergui/__init__.py
framewatchergui/__main__.py
framewatchergui/gui.py
framewatchergui/log.py
framewatchergui/run.py
framewatchergui-0.0.3.dist-info/METADATA
framewatchergui-0.0.3.dist-info/WHEEL
framewatchergui-0.0.3.dist-info/entry_points.txt
framewatchergui-0.0.3.dist-info/top_level.txt
framewatchergui-0.0.3.dist-info/RECORD
