Metadata-Version: 2.1
Name: framewatchergui
Version: 0.0.3
Summary: UNKNOWN
Home-page: https://github.com/alberttxu/framewatchergui
Author: Albert Xu
Author-email: albert.t.xu@gmail.com
License: MIT
Platform: UNKNOWN
Classifier: Programming Language :: Python :: 3
Classifier: License :: OSI Approved :: MIT License
Classifier: Operating System :: OS Independent
Requires-Dist: PySimpleGUI
Requires-Dist: pexpect
